atanu_mlkit/__init__.py
atanu_mlkit/main.py
atanu_mlkit/models/__init__.py
atanu_mlkit/models/unet.py
atanu_mlkit/preprocessing/__init__.py
atanu_mlkit/preprocessing/text_encoder.py
mlkit/__init__.py
mlkit/main.py
mlkit/preprocessing/__init__.py
mlkit/preprocessing/text_encoder.py
mlkit_learn/__init__.py
mlkit_learn/main.py
mlkit_learn/preprocessing/__init__.py
mlkit_learn/preprocessing/text_encoder.py
atanu_mlkit-0.0.3.dist-info/METADATA
atanu_mlkit-0.0.3.dist-info/WHEEL
atanu_mlkit-0.0.3.dist-info/top_level.txt
atanu_mlkit-0.0.3.dist-info/RECORD
